alarm/alarm.v
module alarm (clk, rst, remote, sensors, siren);
  input clk, rst, remote, sensors;
  output reg siren;
  
  // Registradores de estado
  reg [2:0] state;
  
  // Codificação dos estados
  parameter a   = 3'b000,
            at  = 3'b001,
            b   = 3'b010,
            bt  = 3'b011,
            c   = 3'b100;

  initial 
  begin
    state <= a;
  end
  
  // Primeiro procedimento - Definicão próximo estado
  always @(negedge clk, negedge rst) 
  begin
    if(rst == 1'b0) state <=a;
    else begin
      case(state)
        a:begin
          if (remote == 1'b0) state <= a;
          else state <= at;
        end

        at:
        begin
          if(remote == 1'b1) state <= at;
          else state <= b;
        end

        b:
        begin
          if(sensors == 1'b1) state <= c;
          else if(remote == 1'b1) state <= bt;
          else state <= b;
        end

        bt:
        begin
          if(remote == 1'b1) state <= bt;
          else state <= a;
        end

        c:
        begin
          if(remote == 1'b0) state <= c;
          else state <= bt;
        end
      endcase
    end
  end
  
  always @(state) begin
    case(state)
      a:  siren = 1'b0;
      at: siren = 1'b0;
      b:  siren = 1'b0;
      bt: siren = 1'b0;
      c:  siren = 1'b1;
    endcase
  end
    
endmodule

alarm/alarm_tb.v
/* 
iverilog -o alarm.out alarm.v alarm_tb.v && ./alarm.out && gtkwave wave.vcd 
*/

`timescale 1ns/100ps

module alarm_tb;
  reg clk_tb, rst_tb, remote_tb, sensors_tb;
  wire siren_tb;

  alarm uut (.clk(clk_tb), .rst(rst_tb), .remote(remote_tb), .sensors(sensors_tb), .siren(siren_tb));
  
  initial 
  begin
    $monitor("rst_tb=%b",rst_tb);
    $dumpfile("wave.vcd");
    $dumpvars(0, alarm_tb);
  
    clk_tb = 0;
    rst_tb = 1;
    remote_tb = 0;
    sensors_tb = 0;
    
    #10
    rst_tb = 0;
    
    #50
    rst_tb = 1;
    
    #30
    remote_tb = 1;
    
    #80
    remote_tb = 0;
    
    #40
    remote_tb = 1;
    
    #30
    remote_tb = 0;
    
    #50
    remote_tb = 1;
    
    #20
    remote_tb = 0;
    
    #80
    sensors_tb = 1;
    
    #20
    sensors_tb = 0;
    
    #90
    remote_tb = 1;
    
    #30
    remote_tb = 0;
    
    #200
    $finish;
    
  end
  
  always #5 clk_tb = ~clk_tb;

endmodule

alarm/wave.vcd
$date
	Fri Jul 14 01:53:24 2023
$end
$version
	Icarus Verilog
$end
$timescale
	100ps
$end
$scope module alarm_tb $end
$var wire 1 ! siren_tb $end
$var reg 1 " clk_tb $end
$var reg 1 # remote_tb $end
$var reg 1 $ rst_tb $end
$var reg 1 % sensors_tb $end
$scope module uut $end
$var wire 1 " clk $end
$var wire 1 # remote $end
$var wire 1 $ rst $end
$var wire 1 % sensors $end
$var parameter 3 & a $end
$var parameter 3 ' at $end
$var parameter 3 ( b $end
$var parameter 3 ) bt $end
$var parameter 3 * c $end
$var reg 1 ! siren $end
$var reg 3 + state [2:0] $end
$upscope $end
$upscope $end
$enddefinitions $end
$comment Show the parameter values. $end
$dumpall
b100 *
b11 )
b10 (
b1 '
b0 &
$end
#0
$dumpvars
b0 +
0%
1$
0#
0"
0!
$end
#50
1"
#100
0"
0$
#150
1"
#200
0"
#250
1"
#300
0"
#350
1"
#400
0"
#450
1"
#500
0"
#550
1"
#600
0"
1$
#650
1"
#700
0"
#750
1"
#800
0"
#850
1"
#900
b1 +
0"
1#
#950
1"
#1000
0"
#1050
1"
#1100
0"
#1150
1"
#1200
0"
#1250
1"
#1300
0"
#1350
1"
#1400
0"
#1450
1"
#1500
0"
#1550
1"
#1600
0"
#1650
1"
#1700
b10 +
0"
0#
#1750
1"
#1800
0"
#1850
1"
#1900
0"
#1950
1"
#2000
0"
#2050
1"
#2100
b11 +
0"
1#
#2150
1"
#2200
0"
#2250
1"
#2300
0"
#2350
1"
#2400
b0 +
0"
0#
#2450
1"
#2500
0"
#2550
1"
#2600
0"
#2650
1"
#2700
0"
#2750
1"
#2800
0"
#2850
1"
#2900
b1 +
0"
1#
#2950
1"
#3000
0"
#3050
1"
#3100
b10 +
0"
0#
#3150
1"
#3200
0"
#3250
1"
#3300
0"
#3350
1"
#3400
0"
#3450
1"
#3500
0"
#3550
1"
#3600
0"
#3650
1"
#3700
0"
#3750
1"
#3800
0"
#3850
1"
#3900
1!
b100 +
0"
1%
#3950
1"
#4000
0"
#4050
1"
#4100
0"
0%
#4150
1"
#4200
0"
#4250
1"
#4300
0"
#4350
1"
#4400
0"
#4450
1"
#4500
0"
#4550
1"
#4600
0"
#4650
1"
#4700
0"
#4750
1"
#4800
0"
#4850
1"
#4900
0"
#4950
1"
#5000
0!
b11 +
0"
1#
#5050
1"
#5100
0"
#5150
1"
#5200
0"
#5250
1"
#5300
b0 +
0"
0#
