ir_control/ir_control.v
module ir_control (clk, rst, irda);
  input clk, rst, irda;
  integer count;
  
  // Registradores de estado
  reg [2:0] state;
  
  // Codificação dos estados
  parameter s0 = 3'b000,
            s1 = 3'b001,
            s2 = 3'b010,
            s3 = 3'b011;

  reg [2:0] buttons = 3'b000;

  initial 
  begin
    state <= s0;
  end
  
  // Primeiro procedimento - Definicão próximo estado
  always @(negedge clk, posedge rst) 
  begin
    if(rst == 1'b1) state <= s0;
    else begin
      case(state)
        s0:
        begin
          if (irda == 1'b1) state <= s0;
          else state <= s1;
        end

        s1:
        begin
          state <= s2;
        end

        s2:
        begin
          if (count < 10) 
            state <= s2;
          else 
            state <= s3;
        end
      endcase
    end
  end
  
  always @(state or negedge clk) begin
    case(state)
      s0: count = 32'bx;
      s1: count = 0;
      s2: count = count + 1;
      s3: buttons = irda << 2;
    endcase
  end
    
endmodule

ir_control/ir_control_tb.v
/* 
iverilog -o ir.out ir_control.v ir_control_tb.v && ./ir.out && gtkwave wave.vcd 
*/

`timescale 1ns/100ps

module ir_control_tb;
  reg clk_tb, rst_tb, irda_tb;

  ir_control uut (.clk(clk_tb), .rst(rst_tb), .irda(irda_tb));
  
  initial 
  begin
    $monitor("rst_tb=%b",rst_tb);
    $dumpfile("wave.vcd");
    $dumpvars(0, ir_control_tb);
  
    clk_tb = 0;
    rst_tb = 0;
    irda_tb = 1;
    
    #10
    rst_tb = 1;
    
    #50
    rst_tb = 0;
    
    #30
    irda_tb = 1;
    
    #80
    irda_tb = 0;
    
    #40
    irda_tb = 1;
    
    #30
    irda_tb = 0;
    
    #50
    irda_tb = 1;
    
    #20
    irda_tb = 0;
    
    #90
    irda_tb = 1;
    
    #30
    irda_tb = 0;
    
    #200
    $finish;
    
  end
  
  always #5 clk_tb = ~clk_tb;

endmodule

ir_control/wave.vcd
$date
	Fri Jul 14 04:00:19 2023
$end
$version
	Icarus Verilog
$end
$timescale
	100ps
$end
$scope module ir_control_tb $end
$var reg 1 ! clk_tb $end
$var reg 1 " irda_tb $end
$var reg 1 # rst_tb $end
$scope module uut $end
$var wire 1 ! clk $end
$var wire 1 " irda $end
$var wire 1 # rst $end
$var parameter 3 $ s0 $end
$var parameter 3 % s1 $end
$var parameter 3 & s2 $end
$var parameter 3 ' s3 $end
$var reg 3 ( buttons [2:0] $end
$var reg 3 ) state [2:0] $end
$var integer 32 * count [31:0] $end
$upscope $end
$upscope $end
$enddefinitions $end
$comment Show the parameter values. $end
$dumpall
b11 '
b10 &
b1 %
b0 $
$end
#0
$dumpvars
bx *
b0 )
b0 (
0#
1"
0!
$end
#50
1!
#100
0!
1#
#150
1!
#200
0!
#250
1!
#300
0!
#350
1!
#400
0!
#450
1!
#500
0!
#550
1!
#600
0!
0#
#650
1!
#700
0!
#750
1!
#800
0!
#850
1!
#900
0!
#950
1!
#1000
0!
#1050
1!
#1100
0!
#1150
1!
#1200
0!
#1250
1!
#1300
0!
#1350
1!
#1400
0!
#1450
1!
#1500
0!
#1550
1!
#1600
0!
#1650
1!
#1700
b0 *
b1 )
0!
0"
#1750
1!
#1800
b1 *
b10 )
0!
#1850
1!
#1900
b10 *
0!
#1950
1!
#2000
b11 *
0!
#2050
1!
#2100
b100 *
0!
1"
#2150
1!
#2200
b101 *
0!
#2250
1!
#2300
b110 *
0!
#2350
1!
#2400
b111 *
0!
0"
#2450
1!
#2500
b1000 *
0!
#2550
1!
#2600
b1001 *
0!
#2650
1!
#2700
b1010 *
0!
#2750
1!
#2800
b11 )
b1011 *
0!
#2850
1!
#2900
b100 (
0!
1"
#2950
1!
#3000
0!
#3050
1!
#3100
b0 (
0!
0"
#3150
1!
#3200
0!
#3250
1!
#3300
0!
#3350
1!
#3400
0!
#3450
1!
#3500
0!
#3550
1!
#3600
0!
#3650
1!
#3700
0!
#3750
1!
#3800
0!
#3850
1!
#3900
0!
#3950
1!
#4000
b100 (
0!
1"
#4050
1!
#4100
0!
#4150
1!
#4200
0!
#4250
1!
#4300
b0 (
0!
0"
